data_slice-1.0.0.dist-info/licenses/LICENSE
dataslicer/__init__.py
dataslicer/main.py
dataslicer/py.typed
data_slice-1.0.0.dist-info/METADATA
data_slice-1.0.0.dist-info/WHEEL
data_slice-1.0.0.dist-info/top_level.txt
data_slice-1.0.0.dist-info/RECORD
