Metadata-Version: 2.4
Name: data-slice
Version: 1.0.0
Summary: DataSlicer is a powerful and lightweight Python tool designed to efficiently split large CSV and Excel (XLSX) files into smaller, more manageable chunks.
Author-email: Mark Moreno <mark@securehst.com>
License: MIT
Project-URL: Bug Tracker, https://github.com/markm-io/dataslicer/issues
Project-URL: Changelog, https://github.com/markm-io/dataslicer/blob/main/CHANGELOG.md
Project-URL: documentation, https://dataslicer.readthedocs.io
Project-URL: repository, https://github.com/markm-io/dataslicer
Classifier: Development Status :: 2 - Pre-Alpha
Classifier: Intended Audience :: Developers
Classifier: Natural Language :: English
Classifier: Operating System :: OS Independent
Classifier: Programming Language :: Python :: 3.9
Classifier: Programming Language :: Python :: 3.10
Classifier: Programming Language :: Python :: 3.11
Classifier: Programming Language :: Python :: 3.12
Classifier: Programming Language :: Python :: 3.13
Classifier: Topic :: Software Development :: Libraries
Requires-Python: >=3.10
License-File: LICENSE
Requires-Dist: openpyxl>=3.1.5
Requires-Dist: pandas>=2.2.3
Requires-Dist: pathvalidate>=3.2.3
Requires-Dist: rich>=13.9.4
Dynamic: license-file
